diarium_cli/__init__.py
diarium_cli/english_words.txt
diarium_cli/finder.py
diarium_cli/helper.py
diarium_cli/journal.py
diarium_cli/main.py
diarium_cli/slovak_words.txt
diarium_cli-0.2.4.dist-info/LICENSE
diarium_cli-0.2.4.dist-info/METADATA
diarium_cli-0.2.4.dist-info/WHEEL
diarium_cli-0.2.4.dist-info/entry_points.txt
diarium_cli-0.2.4.dist-info/top_level.txt
diarium_cli-0.2.4.dist-info/RECORD
