Metadata-Version: 2.1
Name: diarium-cli
Version: 0.2.4
Summary: CLI tool for journaling app Diarium
Home-page: https://github.com/YelovSK/Diarium-CLI
Author: Yelov
License: Apache License 2.0
Requires-Python: >=3.7
License-File: LICENSE
Requires-Dist: click
Requires-Dist: click-shell
Requires-Dist: rich
Requires-Dist: unidecode
Requires-Dist: nltk
